setup.py
socialauth/__init__.py
socialauth/context_processors.py
socialauth/models.py
socialauth/tests.py
socialauth/urls.py
socialauth/views.py
zero_socialauth.egg-info/PKG-INFO
zero_socialauth.egg-info/SOURCES.txt
zero_socialauth.egg-info/dependency_links.txt
zero_socialauth.egg-info/not-zip-safe
zero_socialauth.egg-info/requires.txt
zero_socialauth.egg-info/top_level.txt