Metadata-Version: 1.0
Name: zero-socialauth
Version: 0.0.2
Summary: Simple app to add social authentication in django projects
Home-page: http://github.com/josezambrana/Zero-Socialauth
Author: Jose Maria Zambrana Arze
Author-email: contact@josezambrana.com
License: apache license v2.0
Keywords: zero socialauth social
Platform: UNKNOWN
